ACKS
COPYING
MANIFEST.in
README.md
pyinotify.py
pyinotify_test.py
setup.py
common/inotify_syscalls.c
old/ChangeLog
old/NEWS
pyinotify_smarkets.egg-info/PKG-INFO
pyinotify_smarkets.egg-info/SOURCES.txt
pyinotify_smarkets.egg-info/dependency_links.txt
pyinotify_smarkets.egg-info/top_level.txt