Metadata-Version: 1.1
Name: pyinotify-smarkets
Version: 1.0.0
Summary: Linux filesystem events monitoring
Home-page: http://github.com/smarkets/pyinotify-smarkets
Author: Smarkets Limited
Author-email: support@smarkets.com
License: MIT License
Download-URL: http://pypi.python.org/pypi/pyinotify-smarkets
Platform: Linux
Classifier: Development Status :: 5 - Production/Stable
Classifier: Environment :: Console
Classifier: Intended Audience :: Developers
Classifier: License :: OSI Approved :: MIT License
Classifier: Natural Language :: English
Classifier: Operating System :: POSIX :: Linux
Classifier: Programming Language :: Python
Classifier: Programming Language :: Python :: 3
Classifier: Programming Language :: Python :: 3.5
Classifier: Programming Language :: Python :: Implementation :: CPython
Classifier: Topic :: Software Development :: Libraries :: Python Modules
Classifier: Topic :: System :: Filesystems
Classifier: Topic :: System :: Monitoring
